LICENSE
README.md
setup.py
aiomox/__init__.py
aiomox/lt_can_client_protocol.py
aiomox/mox_client.py
aiomox/py.typed
aiomox.egg-info/PKG-INFO
aiomox.egg-info/SOURCES.txt
aiomox.egg-info/dependency_links.txt
aiomox.egg-info/requires.txt
aiomox.egg-info/top_level.txt
aiomox.egg-info/zip-safe
aiomox/device/__init__.py
aiomox/device/curtain.py
aiomox/device/device.py
aiomox/device/dimmer.py
aiomox/device/py.typed
aiomox/device/switch.py